cache_middleware/__init__.py
cache_middleware/apps.py
cache_middleware/middlewares.py
cache_middleware/middlewares_celery.py
cache_middleware/task.py
cache_middleware/tests.py
cache_middleware/utils.py
cache_middleware_django-0.0.1.dist-info/METADATA
cache_middleware_django-0.0.1.dist-info/WHEEL
cache_middleware_django-0.0.1.dist-info/top_level.txt
cache_middleware_django-0.0.1.dist-info/RECORD
